databricks/__init__.py
databricks/sqlalchemy/__init__.py
databricks/sqlalchemy/_ddl.py
databricks/sqlalchemy/_parse.py
databricks/sqlalchemy/_types.py
databricks/sqlalchemy/base.py
databricks/sqlalchemy/py.typed
databricks/sqlalchemy/pytest.ini
databricks/sqlalchemy/requirements.py
databricks/sqlalchemy/setup.cfg
databricks_sqlalchemy-2.0.8.dist-info/LICENSE
databricks_sqlalchemy-2.0.8.dist-info/METADATA
databricks_sqlalchemy-2.0.8.dist-info/WHEEL
databricks_sqlalchemy-2.0.8.dist-info/entry_points.txt
databricks_sqlalchemy-2.0.8.dist-info/RECORD
