Metadata-Version: 2.3
Name: databricks-sqlalchemy
Version: 2.0.8
Summary: Databricks SQLAlchemy plugin for Python
License: Apache-2.0
Author: Databricks
Author-email: databricks-sql-connector-maintainers@databricks.com
Requires-Python: >=3.8.0,<4.0.0
Classifier: License :: OSI Approved :: Apache Software License
Classifier: Programming Language :: Python :: 3
Classifier: Programming Language :: Python :: 3.8
Classifier: Programming Language :: Python :: 3.9
Classifier: Programming Language :: Python :: 3.10
Classifier: Programming Language :: Python :: 3.11
Classifier: Programming Language :: Python :: 3.12
Classifier: Programming Language :: Python :: 3.13
Requires-Dist: databricks_sql_connector (>=4.0.0)
Requires-Dist: pyarrow (>=14.0.1)
Requires-Dist: sqlalchemy (>=2.0.21)
Project-URL: Bug Tracker, https://github.com/databricks/databricks-sqlalchemy/issues
Project-URL: Homepage, https://github.com/databricks/databricks-sqlalchemy
